<?xml version="1.0" encoding="utf-8"?>
<!DOCTYPE hibernate-mapping PUBLIC "-//Hibernate/Hibernate Mapping DTD 3.0//EN"
"http://www.hibernate.org/dtd/hibernate-mapping-3.0.dtd">
<!-- 
    Mapping file autogenerated by MyEclipse Persistence Tools
-->
<hibernate-mapping>
    <class name="com.shijing.bean.TbOrderdetail" table="tb_orderdetail" catalog="baobao">
        <id name="id" type="java.lang.Integer">
            <column name="id" />
            <generator class="identity" />
        </id>
        <property name="orderId" type="java.lang.String">
            <column name="orderID" length="50" not-null="true" />
        </property>
        <property name="packageId" type="java.lang.String">
            <column name="packageID" length="50" />
        </property>
        <property name="familyName" type="java.lang.String">
            <column name="familyName" length="20" not-null="true" />
        </property>
        <property name="gender" type="java.lang.String">
            <column name="gender" length="1" not-null="true" />
        </property>
        <property name="wordCount" type="java.lang.String">
            <column name="wordCount" length="1" not-null="true" />
        </property>
        <property name="birthDay" type="java.lang.String">
            <column name="birthDay" length="20" not-null="true" />
        </property>
        <property name="mailInfo" type="java.lang.String">
            <column name="mailInfo" length="50" />
        </property>
        <property name="forbiddenWord" type="java.lang.String">
            <column name="forbiddenWord" length="50" />
        </property>
        <property name="specifyGeneration" type="java.lang.String">
            <column name="specifyGeneration" length="50" />
        </property>
        <property name="birthPlace" type="java.lang.String">
            <column name="birthPlace" length="100" />
        </property>
        <property name="optionRemedy" type="java.lang.String">
            <column name="optionRemedy" length="50" />
        </property>
        <property name="orderState" type="java.lang.String">
            <column name="orderState" length="1" />
        </property>
        <property name="orderTime" type="java.sql.Timestamp">
            <column name="orderTime" length="0" />
        </property>
    </class>
</hibernate-mapping>
